firscript/__init__.py
firscript/engine.py
firscript/execution_context.py
firscript/importer.py
firscript/namespace_registry.py
firscript/parser.py
firscript/script.py
firscript/version.py
firscript/exceptions/__init__.py
firscript/exceptions/base.py
firscript/exceptions/parsing.py
firscript/exceptions/runtime.py
firscript/namespaces/base.py
firscript/namespaces/chart.py
firscript/namespaces/color.py
firscript/namespaces/data.py
firscript/namespaces/input.py
firscript/namespaces/log.py
firscript/namespaces/strategy.py
firscript/namespaces/ta.py
firscript-1.0.0.dist-info/licenses/LICENSE
firscript-1.0.0.dist-info/METADATA
firscript-1.0.0.dist-info/WHEEL
firscript-1.0.0.dist-info/top_level.txt
firscript-1.0.0.dist-info/RECORD
