Metadata-Version: 2.4
Name: firscript
Version: 1.0.0
Summary: A Python-based backtesting engine with a custom scripting system inspired by TradingView's Pine Script
Author: JungleDome
License: MIT License
Project-URL: Documentation, https://github.com/JungleDome/FirScript
Project-URL: Source, https://github.com/JungleDome/FirScript
Project-URL: Tracker, https://github.com/JungleDome/FirScript/issues
Keywords: trading,backtesting,finance,technical analysis,pinescript
Classifier: Development Status :: 4 - Beta
Classifier: Intended Audience :: Financial and Insurance Industry
Classifier: Intended Audience :: Developers
Classifier: License :: OSI Approved :: MIT License
Classifier: Programming Language :: Python :: 3
Classifier: Programming Language :: Python :: 3.8
Classifier: Programming Language :: Python :: 3.9
Classifier: Programming Language :: Python :: 3.10
Classifier: Programming Language :: Python :: 3.11
Classifier: Topic :: Office/Business :: Financial
Classifier: Topic :: Software Development :: Libraries :: Python Modules
Requires-Python: >=3.8
License-File: LICENSE
Requires-Dist: colorama
Requires-Dist: numpy
Requires-Dist: pandas
Requires-Dist: python-dateutil
Requires-Dist: pytz
Requires-Dist: six
Requires-Dist: typing_extensions
Requires-Dist: tzdata
Dynamic: license-file
